Workbook

Sheet commercial invoice
A1: GREAT SHINE HOUSEWARE LTD
A2: ROOM 506, Building 2, No. 58 Tanzhu Road, Minhang District, Shanghai 201108
A6: COMMERCIAL INVOICE
A9: Messr: | B9: GREAT SHINE HOUSEWARE LTD | G9: INVOICE NO.: | I9: COZ-363(COZ-355-363-365)
B10: ROOM 506, Building 2, No. 58 Tanzhu Road,
B11: Minhang District, Shanghai 201108, China | G11: INVOICE Date: | I11: 46290
A13: Ship to: | B13: Sanders Collection Inc.
B14: 10 Hilda Lane, Monsey, NY 10952 , USA
B15: Eli Eleifer
B16: +1 845-738-4832
A18: PO No. | B18: Item. | C18: DESCRIPTION | D18: PACKING SIZE(CM) | E18: Quantities | F18: CBM | G18: Total | H18: PRICE | I18: TOTAL | J18: Numbers
E19: (units) | G19: (CBM) | H19: (USD) | I19: AMOUNT | J19: of package
I20: (USD) | J20: (CTN)
A21: COZ-355 | B21: HH-CB-WRMGRY | C21: Outside:Canvas with PEVA,3 pockets Inside:Peach skin velvet | D21: 58*30*60 | E21: 1008 | F21: 0.1044 | G21: 4.3848 | H21: 6.66 | I21: =H21*E21 -> 6713.28 | J21: 42
A22: COZ-355 | B22: HH-CB-SGEGRN | C22: Outside:Canvas with PEVA,3 pockets Inside:Peach skin velvet | D22: 60*30*58 | E22: 3768 | F22: 0.1044 | G22: 16.3908 | H22: 6.66 | I22: =H22*E22 -> 25094.88 | J22: 157
A23: COZ-363 | B23: SB-HDS-05-BG-V2 | C23: Outer polyester yarn dyed Inisde: nonwoven+Down imitation fiber+polyester paper board 2.0mm | D23: 43*30*40 | E23: 2190 | F23: 0.0516 | G23: ='[1]PACKING LIST '!H15*'[1]PACKING LIST '!I15*'[1]PACKING LIST '!J15/1000000*'[1]PACKING LIST '!G15 -> 7.5336 | H23: 3.43 | I23: =H23*E23 -> 7511.7 | J23: 146
A24: COZ-363 | B24: SB-HDS-05-V2 | C24: Outer polyester yarn dyed Inisde: nonwoven+Down imitation fiber+polyester paper board 2.0mm | D24: 43*30*40 | E24: 6000 | F24: 0.0516 | G24: ='[1]PACKING LIST '!H16*'[1]PACKING LIST '!I16*'[1]PACKING LIST '!J16/1000000*'[1]PACKING LIST '!G16 -> 20.64 | H24: 3.43 | I24: =H24*E24 -> 20580 | J24: 400
A25: COZ-363 | B25: SB-STRGBNCH-15IN-BRN-LTHR | C25: Leather, MDF Board; Non- woven fabric, Paper Board | D25: 47*33.3*40 | E25: 200 | F25: 0.062604 | G25: 3.1302 | H25: 8.65 | I25: =H25*E25 -> 1730 | J25: 50
A26: COZ-363 | B26: SB-STRGBNCH-30IN-PNK-LTHR | C26: Boucle fabric +MDF board+non-woven fabric | D26: 83*39*7 | E26: 70 | F26: 0.022659 | G26: 1.58613 | H26: 16.92 | I26: =H26*E26 -> 1184.4 | J26: 70
A27: COZ-363 | B27: SB-STRGBNCH-15IN-GRN-FBRC | C27: Boucle fabric +MDF board+non-woven fabric | D27: 47*33*40 | E27: 52 | F27: 0.06204 | G27: 0.80652 | H27: 8.66 | I27: =H27*E27 -> 450.32 | J27: 13
A28: COZ-363 | B28: SB-STRGBNCH-43IN-GRN-VLVT | C28: Boucle fabric +MDF board+non-woven fabric | D28: 117*39*7.5 | E28: 200 | F28: 0.0342225 | G28: 6.8445 | H28: 21.97 | I28: =H28*E28 -> 4394 | J28: 200
A29: COZ-363 | B29: SB-STRGBNCH-43IN-LTGRY-LTHR | C29: Boucle fabric +MDF board+non-woven fabric | D29: 117*38.5*7.5 | E29: 50 | F29: 0.03378375 | G29: 1.6891875 | H29: 21.83 | I29: =H29*E29 -> 1091.5 | J29: 50
A30: COZ-365 | B30: HH-CB | C30: Outside:Canvas with PEVA,3 pockets Inside:Peach skin velvet | D30: 58*30*60 | E30: 168 | F30: 0.1044 | G30: 0.7308 | H30: 6.66 | I30: =H30*E30 -> 1118.88 | J30: 7
A31: COZ-365 | B31: HH-CB-MSTRD | C31: Outside:Canvas with PEVA,3 pockets Inside:Peach skin velvet | D31: 58*30*60 | E31: 24 | F31: 0.1044 | G31: 0.1044 | H31: 6.66 | I31: =H31*E31 -> 159.84 | J31: 1
A32: Total | E32: =SUM(E21:E31) -> 13730 | G32: =SUM(G21:G31) -> 63.840938 | I32: =SUM(I21:I31) -> 70028.8 | J32: =SUM(J21:J31) -> 1136
A33: DDP Cost | I33: 17915
A34: Total Amount: | I34: =SUM(I32:I33) -> 87943.8
A35: Deposit Received from COZ-363 | I35: 7388.41
A36: Deposit Received from COZ-355 | I36: 6617.38
A37: Balance Due: | I37: =I34-I35-I36 -> 73938.01
A38: TOTAL AMOUNT : SAY US DOLLARS SEVENTY THREE THOUSAND NINE HUNDRED THIRTY-EIGHT AND ZERO ONE CENTS ONLY
A40: Beneficiary name: Great Shine Houseware Ltd Beneficiary Account Number: 63003420941 Swift Code: CHASHKHHXXX Country/Region: HongKong Beneficiary Address: Units 1260, 12/F, Emperor Group Centre, 288 Hennessy Road, Wan Chai, Hong Kong Beneficiary Bank: JPMorgan Chase Bank N.A., Hong Kong Branch Beneficiary Bank Address: CHARTER HOUSE, 8 CONNAUGHT ROAD, CENTRAL, HONG KONG Bank Code：007 Branch Code: 863

Sheet packing list
A1: ='commercial invoice'!A1 -> GREAT SHINE HOUSEWARE LTD
A2: ='commercial invoice'!A2 -> ROOM 506, Building 2, No. 58 Tanzhu Road, Minhang District, Shanghai 201108
A6: PACKING LIST
A9: Messr: | B9: ='commercial invoice'!B9 -> GREAT SHINE HOUSEWARE LTD | J9: PI NO.: | K9: ='commercial invoice'!I9 -> COZ-363(COZ-355-363-365)
B10: ='commercial invoice'!B10 -> ROOM 506, Building 2, No. 58 Tanzhu Road, | J10: B/L NO.: | K10: EGLV142603382332
B11: ='commercial invoice'!B11 -> Minhang District, Shanghai 201108, China | J11: CONTAINER NO.： | K11: HPCU4900346
J12: SEAL NO.: | K12: EMCVQQ9944
A13: Ship to : | B13: ='commercial invoice'!B13 -> Sanders Collection Inc. | J13: VESSEL/VOY: | K13: OOCL TULIP V. 005E
B14: ='commercial invoice'!B14 -> 10 Hilda Lane, Monsey, NY 10952 , USA | J14: LOADING DATE | K14: 46290
B15: ='commercial invoice'!B15 -> Eli Eleifer | J15: ETD: | K15: 46294
A17: DESTINATION: | B17: NY Port
A19: PO No. | B19: Item. | C19: DESCRIPTION | D19: PACKING SIZE(CM) | E19: Quantities | F19: CBM | G19: Total | H19: G.W. | I19: TOTAL | J19: N.W. | K19: TOTAL | L19: Numbers
E20: (units) | G20: (CBM) | H20: (kgs) | I20: G.W. | J20: (kgs) | K20: N.W. | L20: of package
I21: (kgs) | K21: (kgs) | L21: (CTN)
A22: ='commercial invoice'!A21 -> COZ-355 | B22: ='commercial invoice'!B21 -> HH-CB-WRMGRY | C22: ='commercial invoice'!C21 -> Outside:Canvas with PEVA,3 pockets Inside:Peach skin velvet | D22: ='commercial invoice'!D21 -> 58*30*60 | E22: ='commercial invoice'!E21 -> 1008 | F22: ='commercial invoice'!F21 -> 0.1044 | G22: ='commercial invoice'!G21 -> 4.3848 | H22: 13.2 | I22: =H22*L22 -> 554.4 | J22: 12 | K22: =J22*L22 -> 504 | L22: ='commercial invoice'!J21 -> 42
A23: ='commercial invoice'!A22 -> COZ-355 | B23: ='commercial invoice'!B22 -> HH-CB-SGEGRN | C23: ='commercial invoice'!C22 -> Outside:Canvas with PEVA,3 pockets Inside:Peach skin velvet | D23: ='commercial invoice'!D22 -> 60*30*58 | E23: ='commercial invoice'!E22 -> 3768 | F23: ='commercial invoice'!F22 -> 0.1044 | G23: ='commercial invoice'!G22 -> 16.3908 | H23: 13.2 | I23: =H23*L23 -> 2072.4 | J23: 12 | K23: =J23*L23 -> 1884 | L23: ='commercial invoice'!J22 -> 157
A24: ='commercial invoice'!A23 -> COZ-363 | B24: ='commercial invoice'!B23 -> SB-HDS-05-BG-V2 | C24: ='commercial invoice'!C23 -> Outer polyester yarn dyed Inisde: nonwoven+Down imitation fiber+polyester paper board 2.0mm | D24: ='commercial invoice'!D23 -> 43*30*40 | E24: ='commercial invoice'!E23 -> 2190 | F24: ='commercial invoice'!F23 -> 0.0516 | G24: ='commercial invoice'!G23 -> 7.5336 | H24: 13.2 | I24: =H24*L24 -> 1927.2 | J24: 12 | K24: =J24*L24 -> 1752 | L24: ='commercial invoice'!J23 -> 146
A25: ='commercial invoice'!A24 -> COZ-363 | B25: ='commercial invoice'!B24 -> SB-HDS-05-V2 | C25: ='commercial invoice'!C24 -> Outer polyester yarn dyed Inisde: nonwoven+Down imitation fiber+polyester paper board 2.0mm | D25: ='commercial invoice'!D24 -> 43*30*40 | E25: ='commercial invoice'!E24 -> 6000 | F25: ='commercial invoice'!F24 -> 0.0516 | G25: ='commercial invoice'!G24 -> 20.64 | H25: 13.2 | I25: =H25*L25 -> 5280 | J25: 12 | K25: =J25*L25 -> 4800 | L25: ='commercial invoice'!J24 -> 400
A26: ='commercial invoice'!A25 -> COZ-363 | B26: ='commercial invoice'!B25 -> SB-STRGBNCH-15IN-BRN-LTHR | C26: ='commercial invoice'!C25 -> Leather, MDF Board; Non- woven fabric, Paper Board | D26: ='commercial invoice'!D25 -> 47*33.3*40 | E26: ='commercial invoice'!E25 -> 200 | F26: ='commercial invoice'!F25 -> 0.062604 | G26: ='commercial invoice'!G25 -> 3.1302 | H26: 17.66 | I26: =H26*L26 -> 883 | J26: 15.5 | K26: =J26*L26 -> 775 | L26: ='commercial invoice'!J25 -> 50
A27: ='commercial invoice'!A26 -> COZ-363 | B27: ='commercial invoice'!B26 -> SB-STRGBNCH-30IN-PNK-LTHR | C27: ='commercial invoice'!C26 -> Boucle fabric +MDF board+non-woven fabric | D27: ='commercial invoice'!D26 -> 83*39*7 | E27: ='commercial invoice'!E26 -> 70 | F27: ='commercial invoice'!F26 -> 0.022659 | G27: ='commercial invoice'!G26 -> 1.58613 | H27: 7.8 | I27: =H27*L27 -> 546 | J27: 6.9 | K27: =J27*L27 -> 483 | L27: ='commercial invoice'!J26 -> 70
A28: ='commercial invoice'!A27 -> COZ-363 | B28: ='commercial invoice'!B27 -> SB-STRGBNCH-15IN-GRN-FBRC | C28: ='commercial invoice'!C27 -> Boucle fabric +MDF board+non-woven fabric | D28: ='commercial invoice'!D27 -> 47*33*40 | E28: ='commercial invoice'!E27 -> 52 | F28: ='commercial invoice'!F27 -> 0.06204 | G28: ='commercial invoice'!G27 -> 0.80652 | H28: 17.32 | I28: =H28*L28 -> 225.16 | J28: 16.72 | K28: =J28*L28 -> 217.36 | L28: ='commercial invoice'!J27 -> 13
A29: ='commercial invoice'!A28 -> COZ-363 | B29: ='commercial invoice'!B28 -> SB-STRGBNCH-43IN-GRN-VLVT | C29: ='commercial invoice'!C28 -> Boucle fabric +MDF board+non-woven fabric | D29: ='commercial invoice'!D28 -> 117*39*7.5 | E29: ='commercial invoice'!E28 -> 200 | F29: ='commercial invoice'!F28 -> 0.0342225 | G29: ='commercial invoice'!G28 -> 6.8445 | H29: 11.2 | I29: =H29*L29 -> 2240 | J29: 10.46 | K29: =J29*L29 -> 2092 | L29: ='commercial invoice'!J28 -> 200
A30: ='commercial invoice'!A29 -> COZ-363 | B30: ='commercial invoice'!B29 -> SB-STRGBNCH-43IN-LTGRY-LTHR | C30: ='commercial invoice'!C29 -> Boucle fabric +MDF board+non-woven fabric | D30: ='commercial invoice'!D29 -> 117*38.5*7.5 | E30: ='commercial invoice'!E29 -> 50 | F30: ='commercial invoice'!F29 -> 0.03378375 | G30: ='commercial invoice'!G29 -> 1.6891875 | H30: 11.2 | I30: =H30*L30 -> 560 | J30: 10.46 | K30: =J30*L30 -> 523 | L30: ='commercial invoice'!J29 -> 50
A31: ='commercial invoice'!A30 -> COZ-365 | B31: ='commercial invoice'!B30 -> HH-CB | C31: ='commercial invoice'!C30 -> Outside:Canvas with PEVA,3 pockets Inside:Peach skin velvet | D31: ='commercial invoice'!D30 -> 58*30*60 | E31: ='commercial invoice'!E30 -> 168 | F31: ='commercial invoice'!F30 -> 0.1044 | G31: ='commercial invoice'!G30 -> 0.7308 | H31: 10.3 | I31: =H31*L31 -> 72.1 | J31: 9.4 | K31: =J31*L31 -> 65.8 | L31: ='commercial invoice'!J30 -> 7
A32: ='commercial invoice'!A31 -> COZ-365 | B32: ='commercial invoice'!B31 -> HH-CB-MSTRD | C32: ='commercial invoice'!C31 -> Outside:Canvas with PEVA,3 pockets Inside:Peach skin velvet | D32: ='commercial invoice'!D31 -> 58*30*60 | E32: ='commercial invoice'!E31 -> 24 | F32: ='commercial invoice'!F31 -> 0.1044 | G32: ='commercial invoice'!G31 -> 0.1044 | H32: 10.3 | I32: =H32*L32 -> 10.3 | J32: 9.4 | K32: =J32*L32 -> 9.4 | L32: ='commercial invoice'!J31 -> 1
D34: Total | E34: =SUM(E22:E33) -> 13730 | G34: =SUM(G22:G33) -> 63.840938 | I34: =SUM(I22:I33) -> 14370.56 | K34: =SUM(K22:K33) -> 13105.56 | L34: =SUM(L22:L33) -> 1136
A36: GREAT SHINE HOUSEWARE LTD
A37: SUPPLIER
